django_database_cipher/__init__.py
django_database_cipher/apps.py
django_database_cipher/signals.py
django_database_cipher/backends/__init__.py
django_database_cipher/backends/sqlite3/__init__.py
django_database_cipher/backends/sqlite3/base.py
django_database_cipher/backends/sqlite3/utils.py
django_database_cipher-1.0.1.dist-info/LICENSE
django_database_cipher-1.0.1.dist-info/METADATA
django_database_cipher-1.0.1.dist-info/WHEEL
django_database_cipher-1.0.1.dist-info/top_level.txt
django_database_cipher-1.0.1.dist-info/RECORD
